make_personal_website/__init__.py
make_personal_website-0.2.0.dist-info/METADATA
make_personal_website-0.2.0.dist-info/WHEEL
make_personal_website-0.2.0.dist-info/licenses/LICENSE
make_personal_website-0.2.0.dist-info/RECORD
